looppredictor/__init__.py
looppredictor/annotateloops.py
looppredictor/classifyloops.py
looppredictor/customized_gbrt_trainer.py
looppredictor/looppredictor.py
looppredictor/trainingtool.py
looppredictor/trainingtool_back.py
looppredictor/Bash/ClassifyLoops.sh
looppredictor/Bash/FeatureGenerator.sh
looppredictor/Bash/FeatureGenerator_custom.sh
looppredictor/Bash/FeatureGenerator_nobed.sh
looppredictor/Bash/bedtools
looppredictor/Rscript/GRangesTSS.R
looppredictor/Rscript/GRangesTool.R
looppredictor/Rscript/GRangesTool_neighbor.R
looppredictor/Rscript/MergeFeature.R
looppredictor/Rscript/MergeFeature_complete.R
looppredictor/Rscript/MergeFeature_custom.R
looppredictor-0.4.10.dist-info/LICENSE.txt
looppredictor-0.4.10.dist-info/METADATA
looppredictor-0.4.10.dist-info/WHEEL
looppredictor-0.4.10.dist-info/entry_points.txt
looppredictor-0.4.10.dist-info/top_level.txt
looppredictor-0.4.10.dist-info/RECORD
