Metadata-Version: 2.1
Name: looppredictor
Version: 0.4.10
Summary: Predicting unknown enhancer-mediated genome topology by an ensemble machine learning model
Home-page: https://github.com/bioinfomaticsCSU/LoopPredictor/
Author: Li Tang
Author-email: tangli_csu@csu.edu.cn
License: LICENSE
Platform: UNKNOWN
Requires-Dist: pandas (>=0.24.2)
Requires-Dist: numpy (>=1.16.2)
Requires-Dist: scikit-learn (<0.20.4,>=0.20.3)
Requires-Dist: pathos (>=0.2.3)
